nonebot_plugin_monitor_study/__init__.py
nonebot_plugin_monitor_study-0.2.4.dist-info/METADATA
nonebot_plugin_monitor_study-0.2.4.dist-info/WHEEL
nonebot_plugin_monitor_study-0.2.4.dist-info/entry_points.txt
nonebot_plugin_monitor_study-0.2.4.dist-info/licenses/LICENSE
nonebot_plugin_monitor_study-0.2.4.dist-info/RECORD
