Metadata-Version: 2.4
Name: nonebot-plugin-monitor-study
Version: 0.2.4
Summary: 监控指定群友发言并调用大模型进行劝阻的 NoneBot2 插件（开关状态 JSON 持久化）
License: MIT License
License-File: LICENSE
Keywords: nonebot,nonebot2,nonebot-plugin,qqbot,onebot,onebotv11,llm,oneapi,monitor
Author: TonyLiang
Author-email: tghrtwld@example.com
Requires-Python: >=3.9, <4.0
Classifier: Programming Language :: Python :: 3
Classifier: Programming Language :: Python :: 3 :: Only
Classifier: Programming Language :: Python :: 3.9
Classifier: License :: OSI Approved :: MIT License
Classifier: Framework :: AsyncIO
Classifier: Intended Audience :: Developers
Classifier: Topic :: Communications :: Chat
Provides-Extra: dev
Requires-Dist: build ; extra == "dev"
Requires-Dist: httpx (>=0.27.0)
Requires-Dist: nonebot-adapter-onebot (>=2.4.6)
Requires-Dist: nonebot-plugin-localstore (>=0.6.0)
Requires-Dist: nonebot2 (>=2.4.4)
Requires-Dist: pydantic (>=2.0.0)
Requires-Dist: pyright[nodejs] ; extra == "dev"
Requires-Dist: ruff ; extra == "dev"
Requires-Dist: twine ; extra == "dev"
Project-URL: Homepage, https://github.com/<你的GitHub用户名>/<你的仓库名>
Project-URL: Issues, https://github.com/<你的GitHub用户名>/<你的仓库名>/issues
Project-URL: Repository, https://github.com/<你的GitHub用户名>/<你的仓库名>
